{
	"name": "relationship-dvbztmryhm",
	"properties": {
		"Namespace": {
			"DatabaseName": "Database 1"
		},
		"Name": "relationship-dvbztmryhm",
		"EntityType": "RELATIONSHIP",
		"Origin": {
			"Type": "SPARK"
		},
		"FromTableName": "CustomerAccount",
		"ToTableName": "BillOfLading",
		"ColumnRelationshipInformations": [
			{
				"FromColumnName": "CustomerAccountId",
				"ToColumnName": "ReceivingCustomerAccountId"
			}
		],
		"RelationshipType": 0,
		"Properties": {
			"DerivedModelRelationshipInfo": "{\"baseRelationship\":{\"fromEntity\":\"CustomerAccount.cdm.json/CustomerAccount\",\"toEntity\":\"BillOfLading.cdm.json/BillOfLading\",\"joinPairs\":[{\"fromAttribute\":\"CustomerAccountId\",\"toAttribute\":\"ReceivingCustomerAccountId\"}]}}"
		}
	},
	"type": "RELATIONSHIP"
}