{
	"name": "relationship-jjhbgrtaxh",
	"properties": {
		"Namespace": {
			"DatabaseName": "banking"
		},
		"Name": "relationship-jjhbgrtaxh",
		"EntityType": "RELATIONSHIP",
		"Origin": {
			"Type": "SPARK"
		},
		"FromTableName": "BankingProduct",
		"ToTableName": "PaymentCardProduct",
		"ColumnRelationshipInformations": [
			{
				"FromColumnName": "ProductId",
				"ToColumnName": "ProductId"
			}
		],
		"RelationshipType": 0,
		"Properties": {
			"DerivedModelRelationshipInfo": "{\"baseRelationship\":{\"fromEntity\":\"BankingProduct.cdm.json/BankingProduct\",\"toEntity\":\"PaymentCardProduct.cdm.json/PaymentCardProduct\",\"joinPairs\":[{\"fromAttribute\":\"ProductId\",\"toAttribute\":\"ProductId\"}]}}"
		}
	},
	"type": "RELATIONSHIP"
}